PacketReader/__init__.py
PacketReader/exception.py
PacketReader/packet.py
PacketReader/reader.py
packetreader-1.1.0.dist-info/LICENSE
packetreader-1.1.0.dist-info/METADATA
packetreader-1.1.0.dist-info/WHEEL
packetreader-1.1.0.dist-info/RECORD
