Metadata-Version: 2.1
Name: packetreader
Version: 1.1.0
Summary: A pcap file parser
License: MIT
Author: yuellin
Author-email: linyue92@outlook.com
Requires-Python: >=3.8,<4.0
Classifier: License :: OSI Approved :: MIT License
Classifier: Programming Language :: Python :: 3
Classifier: Programming Language :: Python :: 3.8
Classifier: Programming Language :: Python :: 3.9
Classifier: Programming Language :: Python :: 3.10
Classifier: Programming Language :: Python :: 3.11
